hello_brahim/__init__.py
hello_brahim/core.py
hello_brahim-0.1.0.dist-info/LICENSE
hello_brahim-0.1.0.dist-info/METADATA
hello_brahim-0.1.0.dist-info/WHEEL
hello_brahim-0.1.0.dist-info/top_level.txt
hello_brahim-0.1.0.dist-info/RECORD
