Metadata-Version: 2.1
Name: hello-brahim
Version: 0.1.0
Summary: Une simple librairie Python pour dire bonjour
Home-page: https://github.com/ton-compte/hello_brahim
Author: Brahim EL MEKKAOUI
Author-email: elmekkaoui.brahim@gmail.com
License: MIT
Platform: UNKNOWN
Classifier: Programming Language :: Python :: 3
Classifier: License :: OSI Approved :: MIT License
Classifier: Operating System :: OS Independent
Requires-Python: >=3.7
